pennylane_sphinx_theme/__init__.py
pennylane_sphinx_theme/_version.py
pennylane_sphinx_theme/footer.py
pennylane_sphinx_theme/layout.html
pennylane_sphinx_theme/navbar.py
pennylane_sphinx_theme/theme.conf
pennylane_sphinx_theme/static/favicon.ico
pennylane_sphinx_theme/static/pennylane.svg
pennylane_sphinx_theme-0.26.0.dist-info/LICENSE
pennylane_sphinx_theme-0.26.0.dist-info/METADATA
pennylane_sphinx_theme-0.26.0.dist-info/WHEEL
pennylane_sphinx_theme-0.26.0.dist-info/entry_points.txt
pennylane_sphinx_theme-0.26.0.dist-info/top_level.txt
pennylane_sphinx_theme-0.26.0.dist-info/RECORD
