Metadata-Version: 2.1
Name: pennylane-sphinx-theme
Version: 0.26.0
Summary: Sphinx theme for PennyLane open-source Python packages
Home-page: https://github.com/XanaduAI/pennylane-sphinx-theme
Maintainer: Xanadu Inc.
Maintainer-email: software@xanadu.ai
License: Apache License 2.0
Classifier: Development Status :: 4 - Beta
Classifier: Environment :: Console
Classifier: Intended Audience :: Developers
Classifier: License :: OSI Approved :: Apache Software License
Classifier: Natural Language :: English
Classifier: Operating System :: OS Independent
Classifier: Programming Language :: Python
Classifier: Programming Language :: Python :: 3
Classifier: Programming Language :: Python :: 3.7
Classifier: Programming Language :: Python :: 3.8
Classifier: Programming Language :: Python :: 3.9
Classifier: Programming Language :: Python :: 3.10
Classifier: Programming Language :: Python :: 3.11
Classifier: Programming Language :: Python :: 3.12
Classifier: Topic :: Documentation
Classifier: Topic :: Documentation :: Sphinx
Classifier: Topic :: Software Development
Classifier: Topic :: Software Development :: Documentation
Provides: pennylane_sphinx_theme
License-File: LICENSE
Requires-Dist: sphinx
Requires-Dist: xanadu-sphinx-theme (~=0.17.0)
Requires-Dist: pillow
Requires-Dist: sphinx-gallery
Requires-Dist: docutils
